{
  "resolvedId": "F:/workSpace2024/knowledge-nuxt3/node_modules/swiper/vue/swiper-vue.js",
  "transforms": [
    {
      "name": "vite:load-fallback",
      "result": "/**\n * Swiper Vue 9.4.1\n * Most modern mobile touch slider and framework with hardware accelerated transitions\n * https://swiperjs.com\n *\n * Copyright 2014-2023 Vladimir Kharlampidi\n *\n * Released under the MIT License\n *\n * Released on: June 13, 2023\n */\n\nimport { Swiper } from './swiper.js';\nimport { SwiperSlide } from './swiper-slide.js';\nexport { useSwiperSlide, useSwiper } from './context.js';\nexport { Swiper, SwiperSlide };",
      "start": 1699961615073,
      "end": 1699961615231,
      "sourcemaps": null
    },
    {
      "name": "unocss:transformers:pre",
      "start": 1699961615231,
      "end": 1699961615231,
      "order": "pre"
    },
    {
      "name": "unocss:global:build:scan",
      "start": 1699961615231,
      "end": 1699961615231,
      "order": "pre"
    },
    {
      "name": "nuxt:layer-aliasing",
      "start": 1699961615231,
      "end": 1699961615231,
      "order": "pre"
    },
    {
      "name": "nuxt:server-devonly:transform",
      "start": 1699961615231,
      "end": 1699961615231,
      "order": "pre"
    },
    {
      "name": "nuxt:client-fallback-auto-id",
      "start": 1699961615231,
      "end": 1699961615231,
      "order": "pre"
    },
    {
      "name": "vite:css",
      "start": 1699961615231,
      "end": 1699961615231,
      "order": "normal"
    },
    {
      "name": "vite:esbuild",
      "start": 1699961615232,
      "end": 1699961615232,
      "order": "normal"
    },
    {
      "name": "vite:json",
      "start": 1699961615232,
      "end": 1699961615232,
      "order": "normal"
    },
    {
      "name": "vite:worker",
      "start": 1699961615232,
      "end": 1699961615232,
      "order": "normal"
    },
    {
      "name": "vite:vue",
      "start": 1699961615232,
      "end": 1699961615232,
      "order": "normal"
    },
    {
      "name": "vite:vue-jsx",
      "start": 1699961615232,
      "end": 1699961615232,
      "order": "normal"
    },
    {
      "name": "unocss:transformers:default",
      "start": 1699961615232,
      "end": 1699961615232,
      "order": "normal"
    },
    {
      "name": "replace",
      "start": 1699961615232,
      "end": 1699961615232,
      "order": "normal"
    },
    {
      "name": "nuxt:remove-plugin-metadata",
      "start": 1699961615234,
      "end": 1699961615234,
      "order": "normal"
    },
    {
      "name": "nuxt:chunk-error",
      "start": 1699961615234,
      "end": 1699961615234,
      "order": "normal"
    },
    {
      "name": "nuxt:components:imports",
      "start": 1699961615234,
      "end": 1699961615235,
      "order": "normal"
    },
    {
      "name": "replace",
      "start": 1699961615235,
      "end": 1699961615235,
      "order": "normal"
    },
    {
      "name": "ssr-styles",
      "start": 1699961615235,
      "end": 1699961615235,
      "order": "normal"
    },
    {
      "name": "vite:define",
      "start": 1699961615235,
      "end": 1699961615235,
      "order": "normal"
    },
    {
      "name": "vite:css-post",
      "start": 1699961615235,
      "end": 1699961615235,
      "order": "normal"
    },
    {
      "name": "vite:build-html",
      "start": 1699961615235,
      "end": 1699961615235,
      "order": "normal"
    },
    {
      "name": "vite:worker-import-meta-url",
      "start": 1699961615235,
      "end": 1699961615235,
      "order": "normal"
    },
    {
      "name": "vite:asset-import-meta-url",
      "start": 1699961615235,
      "end": 1699961615235,
      "order": "normal"
    },
    {
      "name": "commonjs",
      "start": 1699961615235,
      "end": 1699961615235,
      "order": "normal"
    },
    {
      "name": "vite:dynamic-import-vars",
      "start": 1699961615235,
      "end": 1699961615235,
      "order": "normal"
    },
    {
      "name": "vite:import-glob",
      "start": 1699961615235,
      "end": 1699961615235,
      "order": "normal"
    },
    {
      "name": "unocss:transformers:post",
      "start": 1699961615235,
      "end": 1699961615235,
      "order": "post"
    },
    {
      "name": "nuxt:composable-keys",
      "start": 1699961615235,
      "end": 1699961615235,
      "order": "post"
    },
    {
      "name": "nuxt:imports-transform",
      "start": 1699961615235,
      "end": 1699961615235,
      "order": "post"
    },
    {
      "name": "unctx:transform",
      "start": 1699961615235,
      "end": 1699961615235,
      "order": "post"
    },
    {
      "name": "nuxt:pages-macros-transform",
      "start": 1699961615235,
      "end": 1699961615235,
      "order": "post"
    },
    {
      "name": "nuxt:runtime-paths-dep",
      "start": 1699961615235,
      "end": 1699961615235,
      "order": "post"
    },
    {
      "name": "element-plus:transform",
      "start": 1699961615235,
      "end": 1699961615235,
      "order": "post"
    },
    {
      "name": "nuxt:route-injection-plugin",
      "start": 1699961615235,
      "end": 1699961615235,
      "order": "post"
    },
    {
      "name": "nuxt:components-loader",
      "start": 1699961615235,
      "end": 1699961615235,
      "order": "post"
    },
    {
      "name": "nuxt:tree-shake-composables:transform",
      "start": 1699961615235,
      "end": 1699961615235,
      "order": "post"
    },
    {
      "name": "vite:build-import-analysis",
      "start": 1699961615235,
      "end": 1699961615235,
      "order": "normal"
    },
    {
      "name": "vite:reporter",
      "start": 1699961615236,
      "end": 1699961615236,
      "order": "normal"
    }
  ]
}
